dlai_grader/__init__.py
dlai_grader/cli.py
dlai_grader/compiler.py
dlai_grader/config.py
dlai_grader/grading.py
dlai_grader/io.py
dlai_grader/notebook.py
dlai_grader/templates.py
dlai_grader/types.py
dlai_grader/templates/Makefile
dlai_grader/templates/grader.py
dlai_grader/templates/submission.ipynb
dlai_grader/templates/copy_assignment_sh/extrafile_n
dlai_grader/templates/copy_assignment_sh/extrafile_y
dlai_grader/templates/dockerfile/data_n_solution_n
dlai_grader/templates/dockerfile/data_n_solution_y
dlai_grader/templates/dockerfile/data_y_solution_n
dlai_grader/templates/dockerfile/data_y_solution_y
dlai_grader/templates/entry_py/solution_n_file_n.py
dlai_grader/templates/entry_py/solution_n_file_y.py
dlai_grader/templates/entry_py/solution_y_file_n.py
dlai_grader/templates/entry_py/solution_y_file_y.py
dlai_grader-2.3.0.dist-info/licenses/LICENSE
dlai_grader-2.3.0.dist-info/METADATA
dlai_grader-2.3.0.dist-info/WHEEL
dlai_grader-2.3.0.dist-info/entry_points.txt
dlai_grader-2.3.0.dist-info/top_level.txt
dlai_grader-2.3.0.dist-info/RECORD
