Metadata-Version: 2.4
Name: dlai-grader
Version: 2.3.0
Summary: Grading utilities for DLAI courses
Home-page: https://github.com/https-deeplearning-ai/grader
Author: Andres Zarta
Author-email: Andres Zarta <andrezb5@gmail.com>
License: MIT
Project-URL: Homepage, https://github.com/https-deeplearning-ai/grader
Classifier: Programming Language :: Python :: 3
Classifier: License :: OSI Approved :: MIT License
Classifier: Operating System :: OS Independent
Requires-Python: >=3.10
License-File: LICENSE
Requires-Dist: nbformat>=5.1.3
Requires-Dist: jupytext>=1.13.0
Dynamic: author
Dynamic: home-page
Dynamic: license-file
